README.rst
setup.py
sornobase/__init__.py
sornobase/algo.py
sornobase/consoleutil.py
sornobase/datetimeutil.py
sornobase/dictutil.py
sornobase/fileutil.py
sornobase/loggingutil.py
sornobase/mathlib.py
sornobase/sornomisc.py
sornobase/stringutil.py
sornobase/webutil.py
sornobase/xmlutil.py
sornobase.egg-info/PKG-INFO
sornobase.egg-info/SOURCES.txt
sornobase.egg-info/dependency_links.txt
sornobase.egg-info/requires.txt
sornobase.egg-info/top_level.txt