Metadata-Version: 1.1
Name: sornobase
Version: 0.2
Summary: Herman Tai's base library for common utilities
Home-page: https://github.com/hermantai/sornobase
Author: Herman Tai
Author-email: htaihm@gmail.com
License: APLv2
Download-URL: https://github.com/hermantai/sornobase/archive/master.zip
Platform: UNKNOWN
Classifier: Development Status :: 3 - Alpha
Classifier: Topic :: Utilities
Classifier: Topic :: Software Development :: Libraries
Classifier: License :: OSI Approved :: Apache Software License
Requires: mock
Requires: python_magic
Requires: python_dateutil
Requires: pytz
Requires: requests
Requires: six
Requires: tzlocal
